speakk/__init__.py
speakk/speak.py
speakk-0.1.1.dist-info/METADATA
speakk-0.1.1.dist-info/WHEEL
speakk-0.1.1.dist-info/top_level.txt
speakk-0.1.1.dist-info/RECORD
