Metadata-Version: 2.1
Name: speakk
Version: 0.1.1
Summary: This code is help you to replace print() function and make your code more attractive.
Home-page: UNKNOWN
Author: Jerry4539
Author-email: <shanayaagraval@gmail.com>
License: UNKNOWN
Platform: UNKNOWN
Classifier: Development Status :: 1 - Planning
Classifier: Intended Audience :: Developers
Classifier: Programming Language :: Python :: 3
Classifier: Operating System :: Unix
Classifier: Operating System :: MacOS :: MacOS X
Classifier: Operating System :: Microsoft :: Windows
Requires-Dist: pyttsx3
Requires-Dist: colorama
